{
  "type": "array",
  "uniqueItems": true,
  "items":
    {
      "$schema": "https://json-schema.org/draft/2020-12/schema",
      "$id": "https://www.coie.uk/schema/contact.json",
      "title": "Contact",
      "description": "A contact in the information exchange",
      "type": "object",
      "properties": {
        "Email": {
          "description": "The unique email for a contact on a contract / project",
          "type": "string",
          "example": "email@home.com",
          "pattern": "^\\S+@\\S+$"
        },
        "CreatedBy": {
          "description": "https://www.thenbs.com/-/media/uk/files/xls/uniclass/2021-04/uniclass2015_ro_v1_5.xlsx code best describing contact",
          "type": "string",
          "enum": ["Ro_1", "Ro_2", "Ro_3"],
          "example": "Ro_10:Management roles"
        },
        "CreatedOn": {
          "description": "https://www.thenbs.com/-/media/uk/files/xls/uniclass/2021-04/uniclass2015_ro_v1_5.xlsx code best describing contact",
          "type": "string",
          "enum": ["Ro_1", "Ro_2", "Ro_3"],
          "example": "Ro_10:Management roles"
        },
        "Category": {
          "description": "https://www.thenbs.com/-/media/uk/files/xls/uniclass/2021-04/uniclass2015_ro_v1_5.xlsx code best describing contact",
          "type": "string",
          "enum": ["Ro_1", "Ro_2", "Ro_3"],
          "example": "Ro_10:Management roles"
        },
        "Company": {
          "description": "Organisation that the contact record represents",
          "type": "string",
          "example": "acme ltd"
        },
        "Phone": {
          "description": "Organisation that the contact record represents",
          "type": "string",
          "example": "+44 (0) 1234 222 333"
        }
      },
      "required": [
        "Email" ,
        "CreatedBy",
        "CreatedOn",
        "Category",
        "Company",
        "Phone"
        ]
    }

  }
